kideo-0.2.5.dist-info/METADATA
kideo-0.2.5.dist-info/WHEEL
kideo/__init__.py
kideo/kideo.cpython-311-x86_64-linux-gnu.so
kideo-0.2.5.dist-info/RECORD
