Metadata-Version: 2.4
Name: kideo
Version: 0.2.5
Summary: Compress videos to WebM with 240p, 15fps, CRF 28
Author-email: vovota company <vovotacompany@gmail.com>
Requires-Python: >=3.7
